packery/__init__.py
packery/__main__.py
packery-0.2.7.dist-info/METADATA
packery-0.2.7.dist-info/WHEEL
packery-0.2.7.dist-info/entry_points.txt
packery-0.2.7.dist-info/top_level.txt
packery-0.2.7.dist-info/RECORD
