Metadata-Version: 2.4
Name: packery
Version: 0.2.7
Summary: Python packaging util for making packing a little bit easier
Home-page: https://github.com/Robert-DeForrest-Reynolds/packery
Author: Robert Lawrence DeForrest Reynolds
License-Expression: MIT
Project-URL: Homepage, https://github.com/Robert-DeForrest-Reynolds/packerys
Project-URL: Repository, https://github.com/Robert-DeForrest-Reynolds/packerys
Keywords: packaging,pip packaging,pypi packaging
Requires-Python: >=3
